fastapi_channels-0.0.1b2.dist-info/METADATA
fastapi_channels-0.0.1b2.dist-info/WHEEL
fastapi_channels-0.0.1b2.dist-info/entry_points.txt
fastapi_channels-0.0.1b2.dist-info/licenses/LICENSE
fastapi_channels/__init__.py
fastapi_channels/api.py
fastapi_channels/channels.py
fastapi_channels/decorators.py
fastapi_channels/exceptions.py
fastapi_channels/lifespan.py
fastapi_channels/metaclssses.py
fastapi_channels/permission.py
fastapi_channels/throttling/__init__.py
fastapi_channels/throttling/base.py
fastapi_channels/throttling/callback.py
fastapi_channels/throttling/depends.py
fastapi_channels/throttling/ext/__init__.py
fastapi_channels/throttling/ext/fastapi_limiter.py
fastapi_channels/throttling/ext/memory.py
fastapi_channels/types.py
fastapi_channels/used.py
fastapi_channels-0.0.1b2.dist-info/RECORD
