Metadata-Version: 2.1
Name: fastapi-channels
Version: 0.0.1b2
Summary: This project provides a simple setup for creating WebSocket communication channels using FastAPI.
Keywords: fastapi,broadcaster,pydantic,fastapi-channels,limits
Author-Email: BXZDYG <banxingzhedeyangguang@gmail.com>
Classifier: Operating System :: OS Independent
Classifier: Intended Audience :: Information Technology
Classifier: Intended Audience :: System Administrators
Classifier: Typing :: Typed
Classifier: Development Status :: 4 - Beta
Classifier: Environment :: Web Environment
Classifier: Framework :: AsyncIO
Classifier: Framework :: FastAPI
Classifier: Framework :: Pydantic
Classifier: Framework :: Pydantic :: 1
Classifier: Intended Audience :: Developers
Classifier: License :: OSI Approved :: MIT License
Classifier: Programming Language :: Python
Classifier: Programming Language :: Python :: 3
Classifier: Programming Language :: Python :: 3 :: Only
Classifier: Programming Language :: Python :: 3.8
Classifier: Programming Language :: Python :: 3.9
Classifier: Programming Language :: Python :: 3.10
Classifier: Programming Language :: Python :: 3.11
Classifier: Programming Language :: Python :: 3.12
Classifier: Topic :: Internet
Classifier: Topic :: Internet :: WWW/HTTP
Classifier: Topic :: Internet :: WWW/HTTP :: HTTP Servers
Classifier: Topic :: Software Development
Classifier: Topic :: Software Development :: Libraries
Classifier: Topic :: Software Development :: Libraries :: Python Modules
Project-URL: Homepage, https://github.com/YGuang233/fastapi-channels
Project-URL: Documentation, https://fc.bxzdyg.cn/
Project-URL: Repository, https://github.com/YGuang233/fastapi-channels
Project-URL: Issues, https://github.com/YGuang233/fastapi-channels/issues
Project-URL: Changelog, https:/fc.bxzdyg.cn/release-notes/
Requires-Python: >=3.8
Requires-Dist: fastapi>=0.110.0
Requires-Dist: broadcaster>=0.3.1
Requires-Dist: limits>=3.12.0
Requires-Dist: pydantic!=1.8,!=1.8.1,!=2.0.0,!=2.0.1,!=2.1.0,<3.0.0,>=1.7.4
Requires-Dist: typing-extensions>=4.8.0
Provides-Extra: standard
Requires-Dist: fastapi[standard]>=0.110.0; extra == "standard"
Provides-Extra: all
Requires-Dist: fastapi[all]>=0.110.0; extra == "all"
Provides-Extra: redis
Requires-Dist: redis; extra == "redis"
Requires-Dist: fastapi_limiter<=0.1.6; extra == "redis"
Provides-Extra: postgres
Requires-Dist: asyncpg; extra == "postgres"
Provides-Extra: kafka
Requires-Dist: aiokafka; extra == "kafka"
Provides-Extra: test
Requires-Dist: pytest; extra == "test"
Requires-Dist: pytest-asyncio; extra == "test"
